README.md
pyproject.toml
setup.cfg
setup.py
src/orf_tools/__init__.py
src/orf_tools/_version.py
src/orf_tools/extend_orfs.py
src/orf_tools.egg-info/PKG-INFO
src/orf_tools.egg-info/SOURCES.txt
src/orf_tools.egg-info/dependency_links.txt
src/orf_tools.egg-info/requires.txt
src/orf_tools.egg-info/top_level.txt