Metadata-Version: 2.1
Name: orf_tools
Version: 0.0.4
Summary: Tools to work with open reading frames (ORFs)
Home-page: https://github.com/pypa/sampleproject
Author: Marco Mariotti and Joan Pallares
Author-email: marco.mariotti@ub.edu
Classifier: Programming Language :: Python :: 3
Classifier: License :: OSI Approved :: MIT License
Classifier: Operating System :: OS Independent
Requires-Python: >=3.6
Requires-Dist: pyfaidx>=0.7.2
Requires-Dist: pandas>=1.3.5
Requires-Dist: easyterm>=1.0.0
Requires-Dist: numpy>=1.17.0
